uturn_cli/__init__.py
uturn_cli/__main__.py
uturn_cli/cli.py
uturn_cli/validate.py
uturn_server/__init__.py
uturn_server/main.py
uturn_server/utility/__init__.py
uturn_server/utility/decorators.py
uturn_server/utility/exceptions.py
uturn_server/utility/gitendpoints.py
uturn_server/utility/gitutility.py
uturn_server/utility/projectendpoints.py
uturn_server/utility/validate.py
uturn_cli-0.0.1.dist-info/LICENSE
uturn_cli-0.0.1.dist-info/METADATA
uturn_cli-0.0.1.dist-info/WHEEL
uturn_cli-0.0.1.dist-info/entry_points.txt
uturn_cli-0.0.1.dist-info/top_level.txt
uturn_cli-0.0.1.dist-info/RECORD
