Metadata-Version: 2.1
Name: uturn-cli
Version: 0.0.1
Summary: CLI utility for Uturn
Home-page: https://github.com/UturnOSS/Uturn-CLI
Author: 0x0elliot
Author-email: adityanrsinha@gmail.com
License: MIT
Platform: UNKNOWN
Classifier: Environment :: Console
Classifier: License :: OSI Approved :: MIT License
Classifier: Programming Language :: Python
Classifier: Programming Language :: Python :: 3 :: Only
Classifier: Topic :: System :: Systems Administration
Requires-Python: >=3.6
License-File: LICENSE
Requires-Dist: click
Requires-Dist: colorama
